[
 {"ID": 54345,"FullName": "Амвросиевка, Украина, Украина","CityName": "Амвросиевка, Украина","OblName": "","Center": "","NalSumLimit": 0,"EngName": "Amvrosiyevka, Ukraina","PostCodeList": "000001","EngFullName": "Amvrosiyevka, Ukraina, Donetskaya obl.","EngOblName": "","CountryCode": 47,"CountryName": "Украина","EngCountryName": "Ukraine" },
 {"ID": 6178,"FullName": "Винница, Украина","CityName": "Винница","OblName": "Винницкая обл.","Center": "","NalSumLimit": 0,"EngName": "Vinnitsa","PostCodeList": "21001,21003,21004,21008,21009,21012,21014,21016,21023,21027,21034,21050,21060","EngFullName": "Vinnitsa, Vinnitskaya obl., Ukraina","EngOblName": "","CountryCode": 47,"CountryName": "Украина","EngCountryName": "Ukraine" },
 {"ID": 79213,"FullName": "Гайсин, Гайсинский р-н, Украина","CityName": "Гайсин, Гайсинский р-н","OblName": "Винницкая обл.","Center": "","NalSumLimit": 0,"EngName": "Gaysin, Gaysinskiy r-n","PostCodeList": "000001","EngFullName": "Gaysin, Gaysinskiy r-n, Ukraina","EngOblName": "","CountryCode": 47,"CountryName": "Украина","EngCountryName": "Ukraine" },
 {"ID": 8817,"FullName": "Луцк, Украина","CityName": "Луцк","OblName": "Волынская обл.","Center": "","NalSumLimit": 0,"EngName": "Lutsk","PostCodeList": "043000","EngFullName": "Lutsk, Volynskaya obl., Ukraina","EngOblName": "","CountryCode": 47,"CountryName": "Украина","EngCountryName": "Ukraine" },
 {"ID": 6953,"FullName": "Днепр, Украина","CityName": "Днепр","OblName": "Днепропетровская обл.","Center": "","NalSumLimit": 0,"EngName": "Dnepropetrovsk","PostCodeList": "49000,49004,49005,49006,49007,49008,49009,49010,49015,49016,49017,49018,49019,49020,49021,49022,49023,49024,49026,49027,49028,49032,49033,49034,49035,49038,49040,49041,49042,49043,49044,49045,49046,49047,49048,49049,49050,49051,49052,49053,49054,49055,49057,49061,49064,49066,49068,49069,49072,49073","EngFullName": "Dnepropetrovsk, Dnepropetrovskaya obl., Ukraina","EngOblName": "","CountryCode": 47,"CountryName": "Украина","EngCountryName": "Ukraine" },
 {"ID": 8288,"FullName": "Кривой Рог, Украина","CityName": "Кривой Рог","OblName": "Днепропетровская обл.","Center": "","NalSumLimit": 0,"EngName": "Krivoy Rog","PostCodeList": "50000,50001,50002,50004,50005,50006,50007,50008,50011,50012,50014,50015,50017,50022,50023,50024,50025,50026,50027,50029,50030,50032,50034,50036,50037,50038,50040,50041,50042,50044,50045,50046,50047,50048,50049,50051,50053,50054,50055,50056,50057,50059,50064,50065,50066,50067,50068,50069,50070,50071,50072,50073,50074,50076,50077,50078,50079,50081,50082,50083,50084,50085,50086,50089,50090,50093,50095,50096,50097,50098,50101,50102,50103,50105,50106","EngFullName": "Krivoy Rog, Dnepropetrovskaya obl., Ukraina","EngOblName": "","CountryCode": 47,"CountryName": "Украина","EngCountryName": "Ukraine" },
 {"ID": 6558,"FullName": "Горловка, Украина","CityName": "Горловка","OblName": "Донецкая обл.","Center": "","NalSumLimit": 0,"EngName": "Gorlovka","PostCodeList": "84601,84603,84604,84605,84607,84609,84610,84611,84612,84613,84614,84617,84618,84622,84624,84625,84626,84627,84628,84629,84630,84632,84634,84635,84637,84639,84646,84647","EngFullName": "Gorlovka, Donetskaya obl., Ukraina","EngOblName": "","CountryCode": 47,"CountryName": "Украина","EngCountryName": "Ukraine" },
 {"ID": 7109,"FullName": "Енакиево, Украина","CityName": "Енакиево","OblName": "Донецкая обл.","Center": "","NalSumLimit": 0,"EngName": "Yenakiyevo","PostCodeList": "000001","EngFullName": "Yenakiyevo, Donetskaya obl., Ukraina","EngOblName": "","CountryCode": 47,"CountryName": "Украина","EngCountryName": "Ukraine" },
 {"ID": 7317,"FullName": "Иловайск, Украина","CityName": "Иловайск","OblName": "Донецкая обл.","Center": "","NalSumLimit": 0,"EngName": "Ilovaysk","PostCodeList": "000001","EngFullName": "Ilovaysk, Donetskaya obl., Ukraina","EngOblName": "","CountryCode": 47,"CountryName": "Украина","EngCountryName": "Ukraine" },
 {"ID": 13956,"FullName": "Комсомольское, Украина","CityName": "Комсомольское","OblName": "Донецкая обл.","Center": "","NalSumLimit": 0,"EngName": "Komsomolskoye","PostCodeList": "87250","EngFullName": "Komsomolskoye, Donetskaya obl, Ukraina","EngOblName": "","CountryCode": 47,"CountryName": "Украина","EngCountryName": "Ukraine" },
 {"ID": 8893,"FullName": "Макеевка, Украина","CityName": "Макеевка","OblName": "Донецкая обл.","Center": "","NalSumLimit": 0,"EngName": "Makeyevka","PostCodeList": "000001","EngFullName": "Makeyevka, Donetskaya obl., Ukraina","EngOblName": "","CountryCode": 47,"CountryName": "Украина","EngCountryName": "Ukraine" },
 {"ID": 8988,"FullName": "Мариуполь, Украина","CityName": "Мариуполь","OblName": "Донецкая обл.","Center": "","NalSumLimit": 0,"EngName": "Mariupol","PostCodeList": "87500,87501,87502,87503,87504,87505,87506,87507,87508,87509,87510,87512,87513,87514,87515,87516,87517,87518,87519,87520,87521,87522,87523,87524,87525,87526,87527,87528,87529,87531,87533,87534,87535,87536,87537,87538,87539,87541,87543,87545,87547,87548,87549,87550,87551,87552,87553,87554,87555,87556,87557,87596,87597","EngFullName": "Mariupol, Donetskaya obl., Ukraina","EngOblName": "","CountryCode": 47,"CountryName": "Украина","EngCountryName": "Ukraine" },
 {"ID": 31255,"FullName": "Моспино, Украина","CityName": "Моспино","OblName": "Донецкая обл.","Center": "","NalSumLimit": 0,"EngName": "Mospino, Ukraina","PostCodeList": "000001","EngFullName": "Mospino, Ukraina","EngOblName": "","CountryCode": 47,"CountryName": "Украина","EngCountryName": "Ukraine" },
 {"ID": 9549,"FullName": "Новоазовск, Украина","CityName": "Новоазовск","OblName": "Донецкая обл.","Center": "","NalSumLimit": 0,"EngName": "Novoazovsk","PostCodeList": "000001","EngFullName": "Novoazovsk, Donetskaya obl., Ukraina","EngOblName": "","CountryCode": 47,"CountryName": "Украина","EngCountryName": "Ukraine" },
 {"ID": 11370,"FullName": "Старобешево, Украина","CityName": "Старобешево","OblName": "Донецкая обл.","Center": "","NalSumLimit": 0,"EngName": "Starobeshevo","PostCodeList": "000001","EngFullName": "Starobeshevo, Donetskaya obl., Ukraina","EngOblName": "","CountryCode": 47,"CountryName": "Украина","EngCountryName": "Ukraine" },
 {"ID": 11581,"FullName": "Тельманово, Украина","CityName": "Тельманово","OblName": "Донецкая обл.","Center": "","NalSumLimit": 0,"EngName": "Telmanovo","PostCodeList": "000001","EngFullName": "Telmanovo, Donetskaya obl., Ukraina","EngOblName": "","CountryCode": 47,"CountryName": "Украина","EngCountryName": "Ukraine" },
 {"ID": 11688,"FullName": "Торез, Украина","CityName": "Торез","OblName": "Донецкая обл.","Center": "","NalSumLimit": 0,"EngName": "Torez","PostCodeList": "000001","EngFullName": "Torez, Donetskaya obl., Ukraina","EngOblName": "","CountryCode": 47,"CountryName": "Украина","EngCountryName": "Ukraine" },
 {"ID": 12261,"FullName": "Харцызск, Украина","CityName": "Харцызск","OblName": "Донецкая обл.","Center": "","NalSumLimit": 0,"EngName": "Khartsyzsk","PostCodeList": "000001","EngFullName": "Khartsyzsk, Donetskaya obl., Ukraina","EngOblName": "","CountryCode": 47,"CountryName": "Украина","EngCountryName": "Ukraine" },
 {"ID": 12703,"FullName": "Шахтерск, Украина","CityName": "Шахтерск","OblName": "Донецкая обл.","Center": "","NalSumLimit": 0,"EngName": "Shakhtersk","PostCodeList": "000001","EngFullName": "Shakhtersk, Donetskaya obl., Ukraina","EngOblName": "","CountryCode": 47,"CountryName": "Украина","EngCountryName": "Ukraine" },
 {"ID": 7163,"FullName": "Житомир, Украина","CityName": "Житомир","OblName": "Житомирская обл.","Center": "","NalSumLimit": 0,"EngName": "Zhitomir","PostCodeList": "10008,10009,10012,10014,10015,10018,10020,10024,10025,10028,10029,10030","EngFullName": "Zhitomir, Zhitomirskaya obl., Ukraina","EngOblName": "","CountryCode": 47,"CountryName": "Украина","EngCountryName": "Ukraine" },
 {"ID": 11847,"FullName": "Ужгород, Украина","CityName": "Ужгород","OblName": "Закарпатская обл.","Center": "","NalSumLimit": 0,"EngName": "Uzhgorod","PostCodeList": "88000,88001,88002,88003,88005,88006,88007,88008,88009,88011,88014,88015,88017,88018,88020,89417","EngFullName": "Uzhgorod, Zakarpatskaya obl., Ukraina","EngOblName": "","CountryCode": 47,"CountryName": "Украина","EngCountryName": "Ukraine" },
 {"ID": 7207,"FullName": "Запорожье, Украина","CityName": "Запорожье","OblName": "Запорожская обл.","Center": "","NalSumLimit": 0,"EngName": "Zaporozhye","PostCodeList": "69001,69002,69004,69005,69006,69007,69008,69009,69012,69013,69014,69017,69021,69026,69027,69031,69032,69034,69035,69037,69039,69040,69041,69050,69057,69059,69060,69061,69063,69065,69067,69068,69069,69071,69076,69077,69081,69083,69091,69092,69093,69095,69096,69097,69098,69104,69105,69106,69107,69114,69118,69120,69121,69123,69124","EngFullName": "Zaporozhye, Zaporozhskaya obl., Ukraina","EngOblName": "","CountryCode": 47,"CountryName": "Украина","EngCountryName": "Ukraine" },
 {"ID": 9093,"FullName": "Мелитополь, Украина","CityName": "Мелитополь","OblName": "Запорожская обл.","Center": "","NalSumLimit": 0,"EngName": "Melitopol","PostCodeList": "072300","EngFullName": "Melitopol, Zaporozhskaya obl., Ukraina","EngOblName": "","CountryCode": 47,"CountryName": "Украина","EngCountryName": "Ukraine" },
 {"ID": 7286,"FullName": "Ивано-Франковск, Украина","CityName": "Ивано-Франковск","OblName": "Ивано-Франковская обл.","Center": "","NalSumLimit": 0,"EngName": "Ivano-Frankovsk","PostCodeList": "076001","EngFullName": "Ivano-Frankovsk, Ivano-Frankovskaya obl., Ukraina","EngOblName": "","CountryCode": 47,"CountryName": "Украина","EngCountryName": "Ukraine" },
 {"ID": 5247,"FullName": "Белая Церковь, Украина","CityName": "Белая Церковь","OblName": "Киевская обл.","Center": "","NalSumLimit": 0,"EngName": "Belaya Tserkov","PostCodeList": "009100","EngFullName": "Belaya Tserkov, Kiyevskaya obl., Ukraina","EngOblName": "","CountryCode": 47,"CountryName": "Украина","EngCountryName": "Ukraine" },
 {"ID": 5537,"FullName": "Борисполь, Украина","CityName": "Борисполь","OblName": "Киевская обл.","Center": "","NalSumLimit": 0,"EngName": "Borispol","PostCodeList": "000001","EngFullName": "Borispol, Kiyevskaya obl., Ukraina","EngOblName": "","CountryCode": 47,"CountryName": "Украина","EngCountryName": "Ukraine" },
 {"ID": 5652,"FullName": "Бровары, Украина","CityName": "Бровары","OblName": "Киевская обл.","Center": "","NalSumLimit": 0,"EngName": "Brovary","PostCodeList": "007400","EngFullName": "Brovary, Kiyevskaya obl., Ukraina","EngOblName": "","CountryCode": 47,"CountryName": "Украина","EngCountryName": "Ukraine" },
 {"ID": 79318,"FullName": "Вышгород, Вышгородский р-н, Украина","CityName": "Вышгород, Вышгородский р-н","OblName": "Киевская обл.","Center": "","NalSumLimit": 0,"EngName": "Vyshgorod, Vyshgorodskiy r-n","PostCodeList": "000001","EngFullName": "Vyshgorod, Vyshgorodskiy r-n, Ukraina","EngOblName": "","CountryCode": 47,"CountryName": "Украина","EngCountryName": "Ukraine" },
 {"ID": 7379,"FullName": "Ирпень, Украина","CityName": "Ирпень","OblName": "Киевская обл.","Center": "","NalSumLimit": 0,"EngName": "Irpen","PostCodeList": "008200","EngFullName": "Irpen, Kiyevskaya obl., Ukraina","EngOblName": "","CountryCode": 47,"CountryName": "Украина","EngCountryName": "Ukraine" },
 {"ID": 7870,"FullName": "Киев, Украина","CityName": "Киев","OblName": "Киевская обл.","Center": "","NalSumLimit": 0,"EngName": "Kiyev","PostCodeList": "01011,01012,01013,01014,01015,01016,01018,01019,01021,01024,01029,01030,01032,01033,01034,01042,01043,01044,01046,01054,01103,01133,01135,01196,01220,02002,02068,02072,02074,02079,02081,02087,02088,02089,02090,02091,02092,02093,02094,02095,02096,02097,02098,02099,02100,02101,02102,02105,02121,02125,02132,02139,02140,02147,02152,02154,02156,02160,02166,02167,02175,02183,02192,02206,02217,02218,02222,02223,02225,02230,02232,03005,03006,03020,03022,03026,03027,03028,03031,03035,03036,03037,03038,03039,03040,03041,03045,03047,03048,03049,03055,03056,03057,03058,03061,03062,03065,03067,03069,03083,03084,03087,03110,03113,03115,03118,03124,03126,03127,03129,03131,03134,03138,03141,03142,03143,03146,03148,03150,03151,03158,03162,03164,03165,03168,03169,03170,03179,03186,03187,03190,03191,03194,04050,04052,04053,04060,04070,04071,04073,04074,04075,04077,04078,04080,04086,04107,04108,04111,04112,04114,04116,04119,04123,04128,04136,04176,04200,04201,04205,04208,04209,04210,04211,04212,04213,0421","EngFullName": "Kiyev, Kiyevskaya obl., Ukraina","EngOblName": "","CountryCode": 47,"CountryName": "Украина","EngCountryName": "Ukraine" },
 {"ID": 43026,"FullName": "Петропавловская Борщаговка, Украина","CityName": "Петропавловская Борщаговка","OblName": "Киевская обл.","Center": "","NalSumLimit": 0,"EngName": "Petropavlovskaya borshchagovka, Kiyevskaya obl","PostCodeList": "000001","EngFullName": "Petropavlovskaya borshchagovka, Kiyevskaya obl, Ukraina","EngOblName": "","CountryCode": 47,"CountryName": "Украина","EngCountryName": "Ukraine" },
 {"ID": 35938,"FullName": "Святопетровское, Украина","CityName": "Святопетровское","OblName": "Киевская обл.","Center": "","NalSumLimit": 0,"EngName": "Svyatopetrovskoye","PostCodeList": "000001","EngFullName": "Svyatopetrovskoye, Ukraina","EngOblName": "","CountryCode": 47,"CountryName": "Украина","EngCountryName": "Ukraine" },
 {"ID": 8819,"FullName": "Львов, Украина","CityName": "Львов","OblName": "Львовская обл.","Center": "","NalSumLimit": 0,"EngName": "Lvov","PostCodeList": "79000,79002,79003,79005,79006,79007,79008,79010,79011,79012,79013,79014,79015,79016,79017,79018,79019,79020,79021,79022,79023,79024,79025,79026,79031,79034,79035,79037,79038,79039,79040,79041,79044,79049,79052,79053,79054,79057,79058,79059,79060,79066,79067,79068,79069,79070,79071,79200,81177","EngFullName": "Lvov, Lvovskaya obl., Ukraina","EngOblName": "","CountryCode": 47,"CountryName": "Украина","EngCountryName": "Ukraine" },
 {"ID": 9520,"FullName": "Николаев, Украина","CityName": "Николаев","OblName": "Львовская обл.","Center": "","NalSumLimit": 0,"EngName": "Nikolayev","PostCodeList": "000001","EngFullName": "Nikolayev, Lvovskaya obl., Ukraina","EngOblName": "","CountryCode": 47,"CountryName": "Украина","EngCountryName": "Ukraine" },
 {"ID": 77941,"FullName": "Трускавець, Украина","CityName": "Трускавець","OblName": "Львовская обл.","Center": "","NalSumLimit": 0,"EngName": "Truskavets-2","PostCodeList": "111111","EngFullName": "Truskavets, Ukraina","EngOblName": "","CountryCode": 47,"CountryName": "Украина","EngCountryName": "Ukraine" },
 {"ID": 9521,"FullName": "Николаев , Украина","CityName": "Николаев ","OblName": "Николаевская обл.","Center": "","NalSumLimit": 0,"EngName": "Nikolayev","PostCodeList": "54001,54002,54003,54007,54010,54015,54017,54018,54020,54022,54024,54025,54028,54029,54030,54031,54034,54036,54037,54038,54039,54040,54042,54046,54048,54049,54050,54051,54052,54055,54056,54058","EngFullName": "Nikolayev, Nikolayevskaya obl., Ukraina","EngOblName": "","CountryCode": 47,"CountryName": "Украина","EngCountryName": "Ukraine" },
 {"ID": 7305,"FullName": "Измаил, Украина","CityName": "Измаил","OblName": "Одесская обл.","Center": "","NalSumLimit": 0,"EngName": "Izmail","PostCodeList": "068600","EngFullName": "Izmail, Odesskaya obl., Ukraina","EngOblName": "","CountryCode": 47,"CountryName": "Украина","EngCountryName": "Ukraine" },
 {"ID": 9816,"FullName": "Одесса, Украина","CityName": "Одесса","OblName": "Одесская обл.","Center": "","NalSumLimit": 0,"EngName": "Odessa","PostCodeList": "65001,65003,65004,65005,65006,65007,65009,65010,65011,65012,65013,65014,65016,65017,65020,65023,65025,65026,65029,65031,65032,65033,65036,65038,65039,65041,65042,65044,65045,65048,65049,65054,65055,65058,65059,65061,65062,65063,65065,65066,65067,65069,65070,65072,65074,65076,65078,65079,65080,65082,65085,65086,65088,65089,65091,65092,65096,65098,65101,65102,65104,65107,65110,65111,65113,65114,65119,65120,65121,65122,65123,65125,65999","EngFullName": "Odessa, Odesskaya obl., Ukraina","EngOblName": "","CountryCode": 47,"CountryName": "Украина","EngCountryName": "Ukraine" },
 {"ID": 8277,"FullName": "Кременчуг, Украина","CityName": "Кременчуг","OblName": "Полтавская обл.","Center": "","NalSumLimit": 0,"EngName": "Kremenchug","PostCodeList": "39600,39601,39602,39603,39605,39610,39611,39612,39617,39619,39621,39622,39623,39625,39627,39628,39630,39631","EngFullName": "Kremenchug, Poltavskaya obl., Ukraina","EngOblName": "","CountryCode": 47,"CountryName": "Украина","EngCountryName": "Ukraine" },
 {"ID": 10310,"FullName": "Полтава, Украина","CityName": "Полтава","OblName": "Полтавская обл.","Center": "","NalSumLimit": 0,"EngName": "Poltava","PostCodeList": "36000,36001,36002,36003,36004,36005,36007,36008,36009,36010,36011,36013,36014,36015,36017,36018,36020,36021,36022,36023,36026,36029,36030,36034,36038,36039,36040,36041,36042","EngFullName": "Poltava, Poltavskaya obl., Ukraina","EngOblName": "","CountryCode": 47,"CountryName": "Украина","EngCountryName": "Ukraine" },
 {"ID": 10641,"FullName": "Ровно, Украина","CityName": "Ровно","OblName": "Ровненская обл.","Center": "","NalSumLimit": 0,"EngName": "Rovno","PostCodeList": "33001,33002,33003,33005,33007,33009,33010,33011,33013,33014,33016,33018,33022,33023,33024,33025,33027,33028","EngFullName": "Rovno, Rovenskaya obl., Ukraina","EngOblName": "","CountryCode": 47,"CountryName": "Украина","EngCountryName": "Ukraine" },
 {"ID": 11445,"FullName": "Сумы, Украина","CityName": "Сумы","OblName": "Сумская обл.","Center": "","NalSumLimit": 0,"EngName": "Sumy","PostCodeList": "40000,40001,40002,40003,40004,40006,40007,40009,40011,40013,40014,40016,40018,40019,40020,40021,40022,40024,40026,40030,40031,40032,40034,40035","EngFullName": "Sumy, Sumskaya obl., Ukraina","EngOblName": "","CountryCode": 47,"CountryName": "Украина","EngCountryName": "Ukraine" },
 {"ID": 38320,"FullName": "Тернополь, Украина","CityName": "Тернополь","OblName": "Тернопольская обл.","Center": "","NalSumLimit": 0,"EngName": "Ternopol","PostCodeList": "046006","EngFullName": "Ternopol , Ukraina","EngOblName": "","CountryCode": 47,"CountryName": "Украина","EngCountryName": "Ukraine" },
 {"ID": 14707,"FullName": "Солоницевка, Украина","CityName": "Солоницевка","OblName": "Харьковская обл.","Center": "","NalSumLimit": 0,"EngName": "Solonitsevka","PostCodeList": "","EngFullName": "Solonitsevka, Ukraina","EngOblName": "","CountryCode": 47,"CountryName": "Украина","EngCountryName": "Ukraine" },
 {"ID": 12262,"FullName": "Харьков, Украина","CityName": "Харьков","OblName": "Харьковская обл.","Center": "","NalSumLimit": 0,"EngName": "Kharkov","PostCodeList": "61001,61002,61003,61004,61007,61009,61010,61013,61015,61016,61017,61019,61020,61022,61023,61024,61025,61029,61030,61031,61032,61033,61034,61036,61037,61038,61039,61040,61044,61045,61046,61047,61051,61052,61054,61057,61058,61060,61064,61066,61067,61068,61070,61071,61072,61075,61077,61080,61081,61082,61085,61089,61090,61091,61093,61096,61098,61099,61100,61103,61105,61106,61107,61108,61109,61110,61111,61112,61115,61118,61120,61121,61123,61124,61128,61129,61135,61136,61137,61138,61139,61140,61143,61144,61145,61146,61153,61157,61158,61161,61162,61166,61168,61170,61171,61172,61174,61176,61177,61183,61184,61195,61202,61204","EngFullName": "Kharkov, Kharkovskaya obl., Ukraina","EngOblName": "","CountryCode": 47,"CountryName": "Украина","EngCountryName": "Ukraine" },
 {"ID": 53877,"FullName": "Новая Каховка, Украина","CityName": "Новая Каховка","OblName": "Херсонская обл.","Center": "","NalSumLimit": 0,"EngName": "Novaya Kakhovka","PostCodeList": "074900","EngFullName": "Novaya Kakhovka, Ukraina","EngOblName": "","CountryCode": 47,"CountryName": "Украина","EngCountryName": "Ukraine" },
 {"ID": 12323,"FullName": "Херсон, Украина","CityName": "Херсон","OblName": "Херсонская обл.","Center": "","NalSumLimit": 0,"EngName": "Kherson","PostCodeList": "073022","EngFullName": "Kherson, Khersonskaya obl., Ukraina","EngOblName": "","CountryCode": 47,"CountryName": "Украина","EngCountryName": "Ukraine" },
 {"ID": 12370,"FullName": "Хмельницкий, Украина","CityName": "Хмельницкий","OblName": "Хмельницкая обл.","Center": "","NalSumLimit": 0,"EngName": "Khmelnitskiy","PostCodeList": "29000,29001,29002,29003,29005,29006,29008,29009,29010,29011,29013,29014,29015,29016,29017,29018,29019,29021,29022,29025,29026,29027","EngFullName": "Khmelnitskiy, Khmelnitskaya obl., Ukraina","EngOblName": "","CountryCode": 47,"CountryName": "Украина","EngCountryName": "Ukraine" },
 {"ID": 12551,"FullName": "Черкассы, Украина","CityName": "Черкассы","OblName": "Черкасская обл.","Center": "","NalSumLimit": 0,"EngName": "Cherkassy","PostCodeList": "18000,18001,18002,18003,18005,18006,18007,18008,18009,18014,18027,18030,18036","EngFullName": "Cherkassy, Cherkasskaya obl., Ukraina","EngOblName": "","CountryCode": 47,"CountryName": "Украина","EngCountryName": "Ukraine" },
 {"ID": 12552,"FullName": "Чернигов, Украина","CityName": "Чернигов","OblName": "Черниговская обл.","Center": "","NalSumLimit": 0,"EngName": "Chernigov","PostCodeList": "14000,14001,14003,14006,14008,14010,14017,14021,14027,14029,14033,14499","EngFullName": "Chernigov, Chernigovskaya obl., Ukraina","EngOblName": "","CountryCode": 47,"CountryName": "Украина","EngCountryName": "Ukraine" },
 {"ID": 12556,"FullName": "Черновцы, Украина","CityName": "Черновцы","OblName": "Черновицкая обл.","Center": "","NalSumLimit": 0,"EngName": "Chernovtsy","PostCodeList": "58001,58002,58003,58004,58007,58012,58019,58022,58029,58050","EngFullName": "Chernovtsy, Chernovitskaya obl., Ukraina","EngOblName": "","CountryCode": 47,"CountryName": "Украина","EngCountryName": "Ukraine" }
]